gitdataminer/__init__.py
gitdataminer/gitlogs/__init__.py
gitdataminer/gitlogs/main.py
gitlogs/__init__.py
gitlogs/main.py
gitdataminer-0.0.3.dist-info/METADATA
gitdataminer-0.0.3.dist-info/WHEEL
gitdataminer-0.0.3.dist-info/top_level.txt
gitdataminer-0.0.3.dist-info/RECORD
